fricon-0.1.0a1.dist-info/METADATA
fricon-0.1.0a1.dist-info/WHEEL
fricon-0.1.0a1.dist-info/entry_points.txt
fricon-0.1.0a1.dist-info/licenses/LICENSE-APACHE
fricon-0.1.0a1.dist-info/licenses/LICENSE-MIT
fricon-0.1.0a1.dist-info/licenses/LICENSES-THIRDPARTY.toml
fricon/__init__.py
fricon/_core.pyd
fricon/_core.pyi
fricon/_helper.py
fricon/py.typed
fricon-0.1.0a1.dist-info/RECORD
