Metadata-Version: 2.4
Name: fricon
Version: 0.1.0a1
Classifier: Development Status :: 3 - Alpha
Classifier: Programming Language :: Python
Classifier: Programming Language :: Rust
Classifier: Programming Language :: Python :: Implementation :: CPython
Classifier: Programming Language :: Python :: Implementation :: PyPy
Classifier: License :: OSI Approved :: MIT License
Classifier: License :: OSI Approved :: Apache Software License
Requires-Dist: numpy>=1.19.3
Requires-Dist: pandas>=2.2.3
Requires-Dist: polars>=1.17.1
Requires-Dist: pyarrow>=17.0.0
License-File: LICENSE-APACHE
License-File: LICENSE-MIT
License-File: LICENSES-THIRDPARTY.toml
Summary: Data collection automation framework.
Keywords: experimental
Author: Jiahao Yuan <kahojyun@icloud.com>
Author-email: Jiahao Yuan <kahojyun@icloud.com>
License: MIT OR Apache-2.0
Requires-Python: >=3.10
Project-URL: Documentation, https://kahojyun.github.io/fricon/
Project-URL: Issues, https://github.com/kahojyun/fricon/issues
Project-URL: Source, https://github.com/kahojyun/fricon
